{
    "problem": "problem-2-Monocytes",
    "ref_normal_samples": [
        "VUHD107",
        "donor 3",
        "SAMN15153963",
        "368C",
        "A26",
        "BG9_33",
        "098C",
        "THD0017",
        "A44",
        "A37",
        "lafy_donor_4",
        "D339",
        "Donor_06",
        "T121",
        "VUHD076",
        "D239",
        "A47",
        "D353",
        "356C",
        "muc9833",
        "THD0006",
        "SAMN15153956",
        "2020-3173-NC007",
        "T166",
        "muc3843",
        "LuT_437",
        "D326",
        "NP26",
        "NP15"
    ],
    "ref_disease_samples": [
        "VUILD63",
        "IPF_04",
        "VUILD61",
        "212I",
        "59I",
        "TILD015",
        "IPF2",
        "123I",
        "010I",
        "IPF_03",
        "VUILD64",
        "221I",
        "IPF3",
        "041I",
        "222I",
        "145I",
        "135I",
        "29I",
        "TILD028",
        "225I",
        "210I",
        "021I",
        "051I",
        "174I",
        "IPF1",
        "053I"
    ],
    "que_normal_samples": [
        "A40",
        "D344",
        "donor 2",
        "T90",
        "226C",
        "Patient_1",
        "THD0012",
        "GSM4593897",
        "DD046Q",
        "NP27",
        "296C",
        "192C",
        "QZY9VQng",
        "465C",
        "Donor_08",
        "VUHD92",
        "T126",
        "NP22",
        "VUHD70",
        "GRO-03",
        "muc4659",
        "GRO-07",
        "dd39p",
        "NP14",
        "NP11",
        "BG9_3",
        "GRO-01",
        "NP35",
        "NP39",
        "284C"
    ],
    "que_disease_samples": [
        "VUILD60",
        "034I",
        "VUILD59",
        "166I",
        "IPF_02",
        "49I",
        "157I",
        "TILD006",
        "138I",
        "063I",
        "158I",
        "209I",
        "228I",
        "022I",
        "177I",
        "179I",
        "VUILD65",
        "TILD010",
        "040I",
        "Cryobiopsy_01",
        "214I",
        "IPF_01",
        "TILD001",
        "025I",
        "47I",
        "VUILD53"
    ],
    "ref_samples": [
        "VUHD107",
        "donor 3",
        "SAMN15153963",
        "368C",
        "A26",
        "BG9_33",
        "098C",
        "THD0017",
        "A44",
        "A37",
        "lafy_donor_4",
        "D339",
        "Donor_06",
        "T121",
        "VUHD076",
        "D239",
        "A47",
        "D353",
        "356C",
        "muc9833",
        "THD0006",
        "SAMN15153956",
        "2020-3173-NC007",
        "T166",
        "muc3843",
        "LuT_437",
        "D326",
        "NP26",
        "NP15",
        "VUILD63",
        "IPF_04",
        "VUILD61",
        "212I",
        "59I",
        "TILD015",
        "IPF2",
        "123I",
        "010I",
        "IPF_03",
        "VUILD64",
        "221I",
        "IPF3",
        "041I",
        "222I",
        "145I",
        "135I",
        "29I",
        "TILD028",
        "225I",
        "210I",
        "021I",
        "051I",
        "174I",
        "IPF1",
        "053I"
    ],
    "que_samples": [
        "A40",
        "D344",
        "donor 2",
        "T90",
        "226C",
        "Patient_1",
        "THD0012",
        "GSM4593897",
        "DD046Q",
        "NP27",
        "296C",
        "192C",
        "QZY9VQng",
        "465C",
        "Donor_08",
        "VUHD92",
        "T126",
        "NP22",
        "VUHD70",
        "GRO-03",
        "muc4659",
        "GRO-07",
        "dd39p",
        "NP14",
        "NP11",
        "BG9_3",
        "GRO-01",
        "NP35",
        "NP39",
        "284C",
        "VUILD60",
        "034I",
        "VUILD59",
        "166I",
        "IPF_02",
        "49I",
        "157I",
        "TILD006",
        "138I",
        "063I",
        "158I",
        "209I",
        "228I",
        "022I",
        "177I",
        "179I",
        "VUILD65",
        "TILD010",
        "040I",
        "Cryobiopsy_01",
        "214I",
        "IPF_01",
        "TILD001",
        "025I",
        "47I",
        "VUILD53"
    ],
    "accuracy": 0.7857142857142857,
    "precision": 0.75,
    "f1": 0.7777777777777778,
    "recall": 0.8076923076923077,
    "outlier_ratio_in_ref_normal": [
        0.023809523809523808,
        0.014678899082568808,
        null,
        null,
        0.01282051282051282,
        null,
        0.08923076923076922,
        0.025423728813559324,
        0.04129793510324484,
        0.034482758620689655,
        0.05786618444846293,
        null,
        0.01639344262295082,
        null,
        null,
        0.03125,
        0.020527859237536656,
        null,
        0.037296037296037296,
        0.06363636363636363,
        0.022222222222222223,
        null,
        null,
        null,
        0.0,
        null,
        null,
        null,
        0.0
    ],
    "outlier_ratio_in_ref_diseased": [
        0.15294117647058825,
        0.0625,
        0.22602739726027396,
        0.3103448275862069,
        0.3559322033898305,
        0.47231833910034604,
        0.23745819397993312,
        0.39880952380952384,
        0.382089552238806,
        0.37894736842105264,
        0.043478260869565216,
        0.16626506024096385,
        0.27209302325581397,
        0.3333333333333333,
        0.20241286863270777,
        0.26342710997442453,
        0.3226837060702875,
        0.3132530120481928,
        0.1912442396313364,
        0.247557003257329,
        0.46511627906976744,
        0.3413897280966767,
        0.3543441226575809,
        0.1981981981981982,
        null,
        0.4588744588744589
    ],
    "outlier_ratio_in_que_normal": [
        0.13048306496390893,
        0.08333333333333333,
        0.09313725490196079,
        null,
        0.18688981868898186,
        0.06168831168831169,
        0.16494845360824742,
        null,
        0.10776545166402536,
        null,
        0.1875,
        0.2838283828382838,
        0.125,
        0.15873015873015872,
        0.008771929824561403,
        0.13259668508287292,
        null,
        null,
        0.0,
        0.3333333333333333,
        0.05555555555555555,
        0.08189655172413793,
        null,
        0.23076923076923078,
        null,
        null,
        null,
        0.031746031746031744,
        null,
        null
    ],
    "outlier_ratio_in_que_diseased": [
        0.10101010101010101,
        0.3032258064516129,
        0.18181818181818182,
        0.14241960183767227,
        0.18181818181818182,
        0.3256997455470738,
        0.23157894736842105,
        0.185,
        0.25555555555555554,
        0.22807017543859648,
        0.2403846153846154,
        0.23015873015873015,
        0.2144212523719165,
        0.2656641604010025,
        0.16188870151770657,
        0.2516778523489933,
        0.23076923076923078,
        null,
        0.32608695652173914,
        0.046511627906976744,
        0.3826086956521739,
        0.09006211180124224,
        0.16972477064220184,
        0.3805970149253731,
        0.45374449339207046,
        0.25
    ]
}